README.md
setup.py
sysmonmq/__init__.py
sysmonmq/action.py
sysmonmq/command.py
sysmonmq/command_sensor.py
sysmonmq/config.py
sysmonmq/const.py
sysmonmq/debug.py
sysmonmq/globals.py
sysmonmq/monitor.py
sysmonmq/mqtt.py
sysmonmq/options.py
sysmonmq/sensor.py
sysmonmq/sysmonmq.py
sysmonmq/util.py
sysmonmq/watcher.py
sysmonmq.egg-info/PKG-INFO
sysmonmq.egg-info/SOURCES.txt
sysmonmq.egg-info/dependency_links.txt
sysmonmq.egg-info/entry_points.txt
sysmonmq.egg-info/requires.txt
sysmonmq.egg-info/top_level.txt