Metadata-Version: 2.1
Name: sysmonmq
Version: 0.0.1
Summary: Client for monitoring and controlling systems over MQTT
Home-page: https://github.com/crowbarz/sysmonmq.git
Author: Crowbar Z
Author-email: crowbarz@outlook.com
License: UNKNOWN
Platform: UNKNOWN
Classifier: Development Status :: 4 - Beta
Classifier: Framework :: AsyncIO
Classifier: Operating System :: POSIX :: Linux
Classifier: Intended Audience :: System Administrators
Classifier: License :: OSI Approved :: MIT License
Classifier: Programming Language :: Python
Classifier: Programming Language :: Python :: 3.6
Classifier: Topic :: Software Development :: Libraries :: Python Modules
Classifier: Topic :: System :: Monitoring
Classifier: Topic :: System :: Networking :: Monitoring
Requires-Python: >=3.6
